<?xml version="1.0" encoding="UTF-8"?>
<billStatus>
  <bill>
    <createDate>2013-06-07T07:01:19Z</createDate>
    <originChamber>Senate</originChamber>
    <cosponsors />
    <title>Export-Import Bank Termination Act</title>
    <actions>
      <item>
        <actionDate>2013-06-06</actionDate>
        <committee>
          <systemCode>ssbk00</systemCode>
          <name>Banking, Housing, and Urban Affairs Committee</name>
        </committee>
        <links />
        <sourceSystem>
          <code>0</code>
          <name>Senate</name>
        </sourceSystem>
        <text>Read twice and referred to the Committee on Banking, Housing, and Urban Affairs.</text>
        <type>IntroReferral</type>
      </item>
      <item>
        <actionCode>10000</actionCode>
        <type>IntroReferral</type>
        <committee />
        <actionDate>2013-06-06</actionDate>
        <sourceSystem>
          <code>9</code>
          <name>Library of Congress</name>
        </sourceSystem>
        <links />
        <text>Introduced in Senate</text>
      </item>
      <actionByCounts>
        <senate>2</senate>
      </actionByCounts>
      <actionTypeCounts>
        <referredToCommittee>1</referredToCommittee>
        <introducedInSenate>1</introducedInSenate>
      </actionTypeCounts>
    </actions>
    <amendments />
    <committeeReports />
    <updateDate>2016-10-25T16:25:03Z</updateDate>
    <subjects>
      <billSubjects>
        <policyArea>
          <name>Foreign Trade and International Finance</name>
        </policyArea>
        <legislativeSubjects>
          <item>
            <name>Competitiveness, trade promotion, trade deficits</name>
          </item>
          <item>
            <name>Department of the Treasury</name>
          </item>
          <item>
            <name>Executive agency funding and structure</name>
          </item>
          <item>
            <name>Export-Import Bank of the United States</name>
          </item>
          <item>
            <name>Government corporations and government-sponsored enterprises</name>
          </item>
          <item>
            <name>Government lending and loan guarantees</name>
          </item>
        </legislativeSubjects>
      </billSubjects>
    </subjects>
    <notes />
    <latestAction>
      <text>Read twice and referred to the Committee on Banking, Housing, and Urban Affairs.</text>
      <actionDate>2013-06-06</actionDate>
      <links />
    </latestAction>
    <sponsors>
      <item>
        <bioguideId>L000577</bioguideId>
        <state>UT</state>
        <fullName>Sen. Lee, Mike [R-UT]</fullName>
        <firstName>Mike</firstName>
        <party>R</party>
        <lastName>Lee</lastName>
        <middleName />
        <byRequestType />
        <identifiers>
          <gpoId>8303</gpoId>
          <lisID>2080</lisID>
          <bioguideId>L000577</bioguideId>
        </identifiers>
      </item>
    </sponsors>
    <relatedBills>
      <item>
        <latestTitle>Export-Import Bank Termination Act</latestTitle>
        <number>2263</number>
        <latestAction>
          <text>Referred to the House Committee on Financial Services.</text>
          <actionDate>2013-06-05</actionDate>
        </latestAction>
        <type>HR</type>
        <congress>113</congress>
        <relationshipDetails>
          <item>
            <identifiedBy>CRS</identifiedBy>
            <type>Related bill</type>
          </item>
        </relationshipDetails>
      </item>
    </relatedBills>
    <laws />
    <cboCostEstimates />
    <committees>
      <billCommittees>
        <item>
          <systemCode>ssbk00</systemCode>
          <subcommittees />
          <type>Standing</type>
          <chamber>Senate</chamber>
          <name>Banking, Housing, and Urban Affairs Committee</name>
          <activities>
            <item>
              <date>2013-06-06T15:49:48Z</date>
              <name>Referred to</name>
            </item>
          </activities>
        </item>
      </billCommittees>
    </committees>
    <calendarNumbers />
    <summaries>
      <billSummaries>
        <item>
          <name>Introduced in Senate</name>
          <actionDesc>Introduced in Senate</actionDesc>
          <lastSummaryUpdateDate>2013-06-12T14:43:52Z</lastSummaryUpdateDate>
          <actionDate>2013-06-06</actionDate>
          <text><![CDATA[<p>Export-Import Bank Termination Act - Abolishes the Export-Import Bank of the United States three years after enactment of this Act.</p>]]></text>
          <versionCode>00</versionCode>
          <updateDate>2013-06-06T04:00:00Z</updateDate>
        </item>
      </billSummaries>
    </summaries>
    <recordedVotes />
    <policyArea>
      <name>Foreign Trade and International Finance</name>
    </policyArea>
    <introducedDate>2013-06-06</introducedDate>
    <billType>S</billType>
    <congress>113</congress>
    <billNumber>1102</billNumber>
    <titles>
      <item>
        <parentTitleType />
        <title>Export-Import Bank Termination Act</title>
        <titleType>Short Titles as Introduced</titleType>
        <chamberCode />
        <chamberName />
      </item>
      <item>
        <parentTitleType />
        <title>A bill to abolish the Export-Import Bank of the United States, and for other purposes.</title>
        <titleType>Official Title as Introduced</titleType>
        <chamberCode />
        <chamberName />
      </item>
      <item>
        <parentTitleType />
        <title>Export-Import Bank Termination Act</title>
        <titleType>Display Title</titleType>
        <chamberCode />
        <chamberName />
      </item>
    </titles>
  </bill>
  <dublinCore xmlns:dc="http://purl.org/dc/elements/1.1/">
    <dc:format>text/xml</dc:format>
    <dc:language>EN</dc:language>
    <dc:rights>Pursuant to Title 17 Section 105 of the United States Code, this file is not subject to copyright protection and is in the public domain.</dc:rights>
    <dc:contributor>Congressional Research Service, Library of Congress</dc:contributor>
    <dc:description>This file contains bill summaries and statuses for federal legislation. A bill summary describes the most significant provisions of a piece of legislation and details the effects the legislative text may have on current law and federal programs. Bill summaries are authored by the Congressional Research Service (CRS) of the Library of Congress. As stated in Public Law 91-510 (2 USC 166 (d)(6)), one of the duties of CRS is "to prepare summaries and digests of bills and resolutions of a public general nature introduced in the Senate or House of Representatives". For more information, refer to the User Guide that accompanies this file.</dc:description>
  </dublinCore>
</billStatus>

