<?xml version="1.0" encoding="UTF-8"?>
<billStatus>
  <bill>
    <latestAction>
      <actionDate>2014-09-18</actionDate>
      <text>Read twice and referred to the Committee on Energy and Natural Resources.</text>
      <links />
    </latestAction>
    <committeeReports />
    <committees>
      <billCommittees>
        <item>
          <chamber>Senate</chamber>
          <systemCode>sseg00</systemCode>
          <activities>
            <item>
              <date>2014-09-18T21:34:23Z</date>
              <name>Referred to</name>
            </item>
          </activities>
          <type>Standing</type>
          <subcommittees />
          <name>Energy and Natural Resources Committee</name>
        </item>
      </billCommittees>
    </committees>
    <laws />
    <createDate>2014-09-19T05:28:32Z</createDate>
    <actions>
      <item>
        <actionDate>2014-09-18</actionDate>
        <committee>
          <systemCode>sseg00</systemCode>
          <name>Energy and Natural Resources Committee</name>
        </committee>
        <links />
        <sourceSystem>
          <code>0</code>
          <name>Senate</name>
        </sourceSystem>
        <text>Read twice and referred to the Committee on Energy and Natural Resources.</text>
        <type>IntroReferral</type>
      </item>
      <item>
        <actionCode>10000</actionCode>
        <type>IntroReferral</type>
        <committee />
        <actionDate>2014-09-18</actionDate>
        <sourceSystem>
          <code>9</code>
          <name>Library of Congress</name>
        </sourceSystem>
        <links />
        <text>Introduced in Senate</text>
      </item>
      <actionByCounts>
        <senate>2</senate>
      </actionByCounts>
      <actionTypeCounts>
        <referredToCommittee>1</referredToCommittee>
        <introducedInSenate>1</introducedInSenate>
      </actionTypeCounts>
    </actions>
    <recordedVotes />
    <amendments />
    <introducedDate>2014-09-18</introducedDate>
    <billNumber>2883</billNumber>
    <policyArea>
      <name>Science, Technology, Communications</name>
    </policyArea>
    <cboCostEstimates />
    <summaries>
      <billSummaries>
        <item>
          <actionDesc>Introduced in Senate</actionDesc>
          <versionCode>00</versionCode>
          <text><![CDATA[<p>Directs the Comptroller General (GAO) to report to Congress on the entrepreneurial impact of technology transfer at the National Laboratories. Requires such report to be based on an evaluation of quantitative performance metrics, including: </p> <ul> <li>the number of licenses granted to small businesses,</li> <li>the numbers of start-up businesses created,</li> <li>the number of cooperative research and development agreements and collaborations involving small businesses and the total number of businesses involved in those agreements and collaborations,</li> <li>the period of time required for the execution of a license, and</li> <li>the number of jobs created.</li> </ul>]]></text>
          <actionDate>2014-09-18</actionDate>
          <name>Introduced in Senate</name>
          <updateDate>2014-09-18T04:00:00Z</updateDate>
          <lastSummaryUpdateDate>2014-10-28T18:34:31Z</lastSummaryUpdateDate>
        </item>
      </billSummaries>
    </summaries>
    <congress>113</congress>
    <subjects>
      <billSubjects>
        <legislativeSubjects>
          <item>
            <name>Business investment and capital</name>
          </item>
          <item>
            <name>Congressional oversight</name>
          </item>
          <item>
            <name>Employee hiring</name>
          </item>
          <item>
            <name>Government buildings, facilities, and property</name>
          </item>
          <item>
            <name>Government studies and investigations</name>
          </item>
          <item>
            <name>Licensing and registrations</name>
          </item>
          <item>
            <name>Performance measurement</name>
          </item>
          <item>
            <name>Research administration and funding</name>
          </item>
          <item>
            <name>Research and development</name>
          </item>
          <item>
            <name>Small business</name>
          </item>
          <item>
            <name>Technology transfer and commercialization</name>
          </item>
        </legislativeSubjects>
        <policyArea>
          <name>Science, Technology, Communications</name>
        </policyArea>
      </billSubjects>
    </subjects>
    <title>A bill to require the Comptroller General of the United States to submit to Congress a report on the entrepreneurial impact of technology transfer at the National Laboratories.</title>
    <updateDate>2016-10-25T16:32:31Z</updateDate>
    <originChamber>Senate</originChamber>
    <titles>
      <item>
        <parentTitleType />
        <titleType>Official Title as Introduced</titleType>
        <title>A bill to require the Comptroller General of the United States to submit to Congress a report on the entrepreneurial impact of technology transfer at the National Laboratories.</title>
        <chamberName />
        <chamberCode />
      </item>
      <item>
        <parentTitleType />
        <titleType>Display Title</titleType>
        <title>A bill to require the Comptroller General of the United States to submit to Congress a report on the entrepreneurial impact of technology transfer at the National Laboratories.</title>
        <chamberName />
        <chamberCode />
      </item>
    </titles>
    <sponsors>
      <item>
        <state>NM</state>
        <firstName>Martin</firstName>
        <byRequestType />
        <bioguideId>H001046</bioguideId>
        <fullName>Sen. Heinrich, Martin [D-NM]</fullName>
        <lastName>Heinrich</lastName>
        <party>D</party>
        <middleName />
        <identifiers>
          <lisID>1937</lisID>
          <gpoId>8056</gpoId>
          <bioguideId>H001046</bioguideId>
        </identifiers>
      </item>
    </sponsors>
    <calendarNumbers />
    <relatedBills />
    <cosponsors />
    <billType>S</billType>
    <notes />
  </bill>
  <dublinCore xmlns:dc="http://purl.org/dc/elements/1.1/">
    <dc:format>text/xml</dc:format>
    <dc:language>EN</dc:language>
    <dc:rights>Pursuant to Title 17 Section 105 of the United States Code, this file is not subject to copyright protection and is in the public domain.</dc:rights>
    <dc:contributor>Congressional Research Service, Library of Congress</dc:contributor>
    <dc:description>This file contains bill summaries and statuses for federal legislation. A bill summary describes the most significant provisions of a piece of legislation and details the effects the legislative text may have on current law and federal programs. Bill summaries are authored by the Congressional Research Service (CRS) of the Library of Congress. As stated in Public Law 91-510 (2 USC 166 (d)(6)), one of the duties of CRS is "to prepare summaries and digests of bills and resolutions of a public general nature introduced in the Senate or House of Representatives". For more information, refer to the User Guide that accompanies this file.</dc:description>
  </dublinCore>
</billStatus>

