<mods xmlns="http://www.loc.gov/mods/v3" xmlns:xsi="http://www.w3.org/2001/XMLSchema-instance" xmlns:xlink="http://www.w3.org/1999/xlink" xsi:schemaLocation="http://www.loc.gov/mods/v3 http://www.loc.gov/standards/mods/v3/mods-3-3.xsd" version="3.3" ID="P0b002ee18d3a2bd6">
<name type="corporate">
 <namePart>United States Government Publishing Office</namePart>
 <role>
  <roleTerm type="text" authority="marcrelator">publisher</roleTerm>
  <roleTerm type="code" authority="marcrelator">pbl</roleTerm>
</role>
 <role>
  <roleTerm type="text" authority="marcrelator">distributor</roleTerm>
  <roleTerm type="code" authority="marcrelator">dst</roleTerm>
</role>
</name>
<name type="corporate">
 <namePart>United States</namePart>
 <namePart>Congress</namePart>
 <namePart>House of Representatives</namePart>
 <role>
  <roleTerm type="text" authority="marcrelator">author</roleTerm>
  <roleTerm type="code" authority="marcrelator">aut</roleTerm>
</role>
 <description>Government Organization</description>
</name>
<typeOfResource>text</typeOfResource>
<genre authority="marcgt">government publication</genre>
<language>
 <languageTerm authority="iso639-2b" type="code">eng</languageTerm>
</language>
<extension>
 <collectionCode>BILLS</collectionCode>
 <searchTitle>To amend title IV of the Public Health Service Act to prohibit sale or transactions relating to human fetal tissue.;Prohibiting the Life-Ending Industry of Fetal Organ Exchange Act;H.R. 3429 (IH)</searchTitle>
 <category>Bills and Statutes</category>
 <waisDatabaseName>114_cong_bills</waisDatabaseName>
 <branch>legislative</branch>
 <dateIngested>2015-08-11</dateIngested>
</extension>
<titleInfo>
 <title>To amend title IV of the Public Health Service Act to prohibit sale or transactions relating to human fetal tissue.</title>
</titleInfo>
<titleInfo type="alternative">
 <title>Prohibiting the Life-Ending Industry of Fetal Organ Exchange Act</title>
</titleInfo>
<titleInfo type="alternative">
 <title>H.R. 3429 (IH)</title>
</titleInfo>
<originInfo>
 <publisher>U.S. Government Publishing Office</publisher>
 <dateIssued encoding="w3cdtf">2015-07-29</dateIssued>
 <issuance>monographic</issuance>
</originInfo>
<physicalDescription>
 <note type="source content type">deposited</note>
 <digitalOrigin>born digital</digitalOrigin>
 <extent>2 p.</extent>
</physicalDescription>
<classification authority="sudocs">Y 1.6:</classification>
<classification authority="sudocs">Y 1.4/6:</classification>
<identifier type="local">P0b002ee18d3a2bd6</identifier>
<identifier type="uri">https://www.gpo.gov/fdsys/pkg/BILLS-114hr3429ih</identifier>
<identifier type="preferred citation">H.R. 3429</identifier>
<identifier type="stock number">021-610-00252-9</identifier>
<identifier type="Parent ILS system id">000501532</identifier>
<identifier type="Child ILS system id">000325573</identifier>
<identifier type="Parent ILS title">Congressional bills</identifier>
<identifier type="Child ILS title">House bills</identifier>
<identifier type="former package identifier">f:h3429_ih.txt</identifier>
<location xmlns:exslt="http://exslt.org/common">
 <url access="object in context" displayLabel="Content Detail">https://www.gpo.gov/fdsys/pkg/BILLS-114hr3429ih/content-detail.html</url>
 <url access="raw object" displayLabel="HTML rendition">https://www.gpo.gov/fdsys/pkg/BILLS-114hr3429ih/html/BILLS-114hr3429ih.htm</url>
 <url access="raw object" displayLabel="PDF rendition">https://www.gpo.gov/fdsys/pkg/BILLS-114hr3429ih/pdf/BILLS-114hr3429ih.pdf</url>
 <url access="raw object" displayLabel="XML rendition">https://www.gpo.gov/fdsys/pkg/BILLS-114hr3429ih/xml/BILLS-114hr3429ih.xml</url>
</location>
<accessCondition type="GPO scope determination">fdlp</accessCondition>
<recordInfo>
 <recordContentSource authority="marcorg">DGPO</recordContentSource>
 <recordCreationDate encoding="w3cdtf">2015-08-11</recordCreationDate>
 <recordChangeDate encoding="w3cdtf">2016-10-11</recordChangeDate>
 <recordIdentifier source="DGPO">BILLS-114hr3429ih</recordIdentifier>
 <recordOrigin>machine generated</recordOrigin>
 <languageOfCataloging>
  <languageTerm authority="iso639-2b" type="code">eng</languageTerm>
</languageOfCataloging>
</recordInfo>
<name type="personal">
 <namePart>Kevin Yoder</namePart>
 <affiliation>United States House of Representatives</affiliation>
 <role>
  <roleTerm type="text" authority="marcrelator">sponsor</roleTerm>
  <roleTerm type="code" authority="marcrelator">spn</roleTerm>
</role>
 <description>United States Congress Member</description>
</name>
<name type="personal">
 <namePart>Trent Franks</namePart>
 <affiliation>United States House of Representatives</affiliation>
 <role>
  <roleTerm type="text">cosponsor</roleTerm>
</role>
 <description>United States Congress Member</description>
</name>
<name type="personal">
 <namePart>Chris Stewart</namePart>
 <affiliation>United States House of Representatives</affiliation>
 <role>
  <roleTerm type="text">cosponsor</roleTerm>
</role>
 <description>United States Congress Member</description>
</name>
<name type="personal">
 <namePart>Sean P. Duffy</namePart>
 <affiliation>United States House of Representatives</affiliation>
 <role>
  <roleTerm type="text">cosponsor</roleTerm>
</role>
 <description>United States Congress Member</description>
</name>
<name type="personal">
 <namePart>Randy Neugebauer</namePart>
 <affiliation>United States House of Representatives</affiliation>
 <role>
  <roleTerm type="text">cosponsor</roleTerm>
</role>
 <description>United States Congress Member</description>
</name>
<name type="personal">
 <namePart>John Shimkus</namePart>
 <affiliation>United States House of Representatives</affiliation>
 <role>
  <roleTerm type="text">cosponsor</roleTerm>
</role>
 <description>United States Congress Member</description>
</name>
<name type="personal">
 <namePart>Walter B. Jones Jr.</namePart>
 <affiliation>United States House of Representatives</affiliation>
 <role>
  <roleTerm type="text">cosponsor</roleTerm>
</role>
 <description>United States Congress Member</description>
</name>
<name type="personal">
 <namePart>Charles J. &quot;Chuck&quot; Fleischmann</namePart>
 <affiliation>United States House of Representatives</affiliation>
 <role>
  <roleTerm type="text">cosponsor</roleTerm>
</role>
 <description>United States Congress Member</description>
</name>
<name type="personal">
 <namePart>Kenny Marchant</namePart>
 <affiliation>United States House of Representatives</affiliation>
 <role>
  <roleTerm type="text">cosponsor</roleTerm>
</role>
 <description>United States Congress Member</description>
</name>
<name type="personal">
 <namePart>Trey Gowdy</namePart>
 <affiliation>United States House of Representatives</affiliation>
 <role>
  <roleTerm type="text">cosponsor</roleTerm>
</role>
 <description>United States Congress Member</description>
</name>
<name type="personal">
 <namePart>Andy Harris</namePart>
 <affiliation>United States House of Representatives</affiliation>
 <role>
  <roleTerm type="text">cosponsor</roleTerm>
</role>
 <description>United States Congress Member</description>
</name>
<name type="personal">
 <namePart>Brian Babin</namePart>
 <affiliation>United States House of Representatives</affiliation>
 <role>
  <roleTerm type="text">cosponsor</roleTerm>
</role>
 <description>United States Congress Member</description>
</name>
<name type="personal">
 <namePart>Lynn Jenkins</namePart>
 <affiliation>United States House of Representatives</affiliation>
 <role>
  <roleTerm type="text">cosponsor</roleTerm>
</role>
 <description>United States Congress Member</description>
</name>
<name type="personal">
 <namePart>Stevan Pearce</namePart>
 <affiliation>United States House of Representatives</affiliation>
 <role>
  <roleTerm type="text">cosponsor</roleTerm>
</role>
 <description>United States Congress Member</description>
</name>
<name type="personal">
 <namePart>Chris Collins</namePart>
 <affiliation>United States House of Representatives</affiliation>
 <role>
  <roleTerm type="text">cosponsor</roleTerm>
</role>
 <description>United States Congress Member</description>
</name>
<name type="personal">
 <namePart>Charles W. Boustany, Jr.</namePart>
 <affiliation>United States House of Representatives</affiliation>
 <role>
  <roleTerm type="text">cosponsor</roleTerm>
</role>
 <description>United States Congress Member</description>
</name>
<name type="personal">
 <namePart>Robert Pittenger</namePart>
 <affiliation>United States House of Representatives</affiliation>
 <role>
  <roleTerm type="text">cosponsor</roleTerm>
</role>
 <description>United States Congress Member</description>
</name>
<name type="personal">
 <namePart>Jeff Duncan</namePart>
 <affiliation>United States House of Representatives</affiliation>
 <role>
  <roleTerm type="text">cosponsor</roleTerm>
</role>
 <description>United States Congress Member</description>
</name>
<name type="personal">
 <namePart>Joe Barton</namePart>
 <affiliation>United States House of Representatives</affiliation>
 <role>
  <roleTerm type="text">cosponsor</roleTerm>
</role>
 <description>United States Congress Member</description>
</name>
<name type="personal">
 <namePart>Mike Kelly</namePart>
 <affiliation>United States House of Representatives</affiliation>
 <role>
  <roleTerm type="text">cosponsor</roleTerm>
</role>
 <description>United States Congress Member</description>
</name>
<name type="corporate">
 <namePart>United States</namePart>
 <namePart>Congress</namePart>
 <namePart>House of Representatives</namePart>
 <namePart>Committee on Energy and Commerce</namePart>
 <role>
  <roleTerm type="text" authority="marcrelator">associated name</roleTerm>
  <roleTerm type="code" authority="marcrelator">asn</roleTerm>
</role>
</name>
<relatedItem xmlns:exslt="http://exslt.org/common" type="isReferencedBy">
 <titleInfo>
  <title>United States Code</title>
  <partNumber>Title 42 Section 298g</partNumber>
</titleInfo>
 <identifier type="USC citation">42 U.S.C. 298g</identifier>
</relatedItem>
<extension>
 <docClass>hr</docClass>
 <accessId>BILLS-114hr3429ih</accessId>
 <congress>114</congress>
 <session>1</session>
 <originChamber>HOUSE</originChamber>
 <currentChamber>HOUSE</currentChamber>
 <billNumber>3429</billNumber>
 <billVersion reprint="false">ih</billVersion>
 <fileSuffix>ih</fileSuffix>
 <shortTitle type="measure">Prohibiting the Life-Ending Industry of Fetal Organ Exchange Act</shortTitle>
 <officialTitle>To amend title IV of the Public Health Service Act to prohibit sale or transactions relating to human fetal tissue.</officialTitle>
 <action date="2015-07-29">Mr. Yoder (for himself, Mr. Franks of Arizona, Mr. Stewart, Mr. Duffy, Mr. Neugebauer, Mr. Shimkus, Mr. Jones, Mr. Fleischmann, Mr. Marchant, Mr. Gowdy, Mr. Harris, Mr. Babin, Ms. Jenkins of Kansas, Mr. Pearce, Mr. Collins of New York, Mr. Boustany, Mr. Pittenger, Mr. Duncan of South Carolina, Mr. Barton, and Mr. Kelly of Pennsylvania) introduced the following bill; which was referred to the Committee on Energy and Commerce</action>
 <congCommittee authorityId="hsif00" chamber="H" congress="114" type="S">
                      <name type="authority-standard">Committee on Energy and Commerce</name>
                      <name type="authority-short">Energy and Commerce</name>
                </congCommittee>
 <congMember authorityId="2021" bioGuideId="Y000063" chamber="H" congress="114" gpoId="7951" party="R" role="SPONSOR" state="KS">
                      <name type="parsed">Mr. Yoder</name>
                      <name type="authority-fnf">Kevin Yoder</name>
                      <name type="authority-lnf">Yoder, Kevin</name>
                </congMember>
 <congMember authorityId="1707" bioGuideId="F000448" chamber="H" congress="114" gpoId="7799" party="R" role="COSPONSOR" state="AZ">
                      <name type="parsed">Mr. Franks of Arizona</name>
                      <name type="authority-fnf">Trent Franks</name>
                      <name type="authority-lnf">Franks, Trent</name>
                </congMember>
 <congMember authorityId="2168" bioGuideId="S001192" chamber="H" congress="114" party="R" role="COSPONSOR" state="UT">
                      <name type="parsed">Mr. Stewart</name>
                      <name type="authority-fnf">Chris Stewart</name>
                      <name type="authority-lnf">Stewart, Chris</name>
                </congMember>
 <congMember authorityId="2072" bioGuideId="D000614" chamber="H" congress="114" gpoId="8220" party="R" role="COSPONSOR" state="WI">
                      <name type="parsed">Mr. Duffy</name>
                      <name type="authority-fnf">Sean P. Duffy</name>
                      <name type="authority-lnf">Duffy, Sean P.</name>
                      <name type="authority-other">Mr. Sean Duffy</name>
                </congMember>
 <congMember authorityId="1758" bioGuideId="N000182" chamber="H" congress="114" gpoId="8175" party="R" role="COSPONSOR" state="TX">
                      <name type="parsed">Mr. Neugebauer</name>
                      <name type="authority-fnf">Randy Neugebauer</name>
                      <name type="authority-lnf">Neugebauer, Randy</name>
                </congMember>
 <congMember authorityId="1527" bioGuideId="S000364" chamber="H" congress="114" gpoId="7939" party="R" role="COSPONSOR" state="IL">
                      <name type="parsed">Mr. Shimkus</name>
                      <name type="authority-fnf">John Shimkus</name>
                      <name type="authority-lnf">Shimkus, John</name>
                      <name type="authority-other">John M. Shimkus</name>
                </congMember>
 <congMember authorityId="612" bioGuideId="J000255" chamber="H" congress="114" gpoId="8026" party="R" role="COSPONSOR" state="NC">
                      <name type="parsed">Mr. Jones</name>
                      <name type="authority-fnf">Walter B. Jones Jr.</name>
                      <name type="authority-lnf">Jones, Walter B., Jr.</name>
                      <name type="authority-other">Walter Jones Jr.</name>
                </congMember>
 <congMember authorityId="2061" bioGuideId="F000459" chamber="H" congress="114" gpoId="8150" party="R" role="COSPONSOR" state="TN">
                      <name type="parsed">Mr. Fleischmann</name>
                      <name type="authority-fnf">Charles J. &quot;Chuck&quot; Fleischmann</name>
                      <name type="authority-lnf">Fleischmann, Charles J. &quot;Chuck&quot;</name>
                      <name type="authority-other">Mr. Charles Fleischmann</name>
                </congMember>
 <congMember authorityId="1806" bioGuideId="M001158" chamber="H" congress="114" gpoId="8766" party="R" role="COSPONSOR" state="TX">
                      <name type="parsed">Mr. Marchant</name>
                      <name type="authority-fnf">Kenny Marchant</name>
                      <name type="authority-lnf">Marchant, Kenny</name>
                </congMember>
 <congMember authorityId="2058" bioGuideId="G000566" chamber="H" congress="114" gpoId="8144" party="R" role="COSPONSOR" state="SC">
                      <name type="parsed">Mr. Gowdy</name>
                      <name type="authority-fnf">Trey Gowdy</name>
                      <name type="authority-lnf">Gowdy, Trey</name>
                </congMember>
 <congMember authorityId="2026" bioGuideId="H001052" chamber="H" congress="114" gpoId="7976" party="R" role="COSPONSOR" state="MD">
                      <name type="parsed">Mr. Harris</name>
                      <name type="authority-fnf">Andy Harris</name>
                      <name type="authority-lnf">Harris, Andy</name>
                </congMember>
 <congMember authorityId="2270" bioGuideId="B001291" chamber="H" congress="114" party="R" role="COSPONSOR" state="TX">
                      <name type="parsed">Mr. Babin</name>
                      <name type="authority-fnf">Brian Babin</name>
                      <name type="authority-lnf">Babin, Brian</name>
                </congMember>
 <congMember authorityId="1921" bioGuideId="J000290" chamber="H" congress="114" gpoId="7950" party="R" role="COSPONSOR" state="KS">
                      <name type="parsed">Ms. Jenkins of Kansas</name>
                      <name type="authority-fnf">Lynn Jenkins</name>
                      <name type="authority-lnf">Jenkins, Lynn</name>
                </congMember>
 <congMember authorityId="1738" bioGuideId="P000588" chamber="H" congress="114" gpoId="8057" party="R" role="COSPONSOR" state="NM">
                      <name type="parsed">Mr. Pearce</name>
                      <name type="authority-fnf">Stevan Pearce</name>
                      <name type="authority-lnf">Pearce, Stevan</name>
                </congMember>
 <congMember authorityId="2151" bioGuideId="C001092" chamber="H" congress="114" party="R" role="COSPONSOR" state="NY">
                      <name type="parsed">Mr. Collins of New York</name>
                      <name type="authority-fnf">Chris Collins</name>
                      <name type="authority-lnf">Collins, Chris</name>
                </congMember>
 <congMember authorityId="1787" bioGuideId="B001255" chamber="H" congress="114" gpoId="7965" party="R" role="COSPONSOR" state="LA">
                      <name type="parsed">Mr. Boustany</name>
                      <name type="authority-fnf">Charles W. Boustany, Jr.</name>
                      <name type="authority-lnf">Boustany, Charles W., Jr.</name>
                      <name type="authority-other">Mr. Charles Boustany Jr.</name>
                </congMember>
 <congMember authorityId="2141" bioGuideId="P000606" chamber="H" congress="114" party="R" role="COSPONSOR" state="NC">
                      <name type="parsed">Mr. Pittenger</name>
                      <name type="authority-fnf">Robert Pittenger</name>
                      <name type="authority-lnf">Pittenger, Robert</name>
                </congMember>
 <congMember authorityId="2057" bioGuideId="D000615" chamber="H" congress="114" gpoId="8143" party="R" role="COSPONSOR" state="SC">
                      <name type="parsed">Mr. Duncan of South Carolina</name>
                      <name type="authority-fnf">Jeff Duncan</name>
                      <name type="authority-lnf">Duncan, Jeff</name>
                </congMember>
 <congMember authorityId="62" bioGuideId="B000213" chamber="H" congress="114" gpoId="8162" party="R" role="COSPONSOR" state="TX">
                      <name type="parsed">Mr. Barton</name>
                      <name type="authority-fnf">Joe Barton</name>
                      <name type="authority-lnf">Barton, Joe</name>
                      <name type="authority-other">Joe L. Barton</name>
                </congMember>
 <congMember authorityId="2051" bioGuideId="K000376" chamber="H" congress="114" gpoId="8708" party="R" role="COSPONSOR" state="PA">
                      <name type="parsed">Mr. Kelly of Pennsylvania</name>
                      <name type="authority-fnf">Mike Kelly</name>
                      <name type="authority-lnf">Kelly, Mike</name>
                </congMember>
 <isPrivate>false</isPrivate>
 <isAppropriation>false</isAppropriation>
 <USCode title="42">
                      <section number="298g"></section>
                </USCode>
</extension>
</mods>