<mods xmlns="http://www.loc.gov/mods/v3" xmlns:xsi="http://www.w3.org/2001/XMLSchema-instance" xmlns:xlink="http://www.w3.org/1999/xlink" xsi:schemaLocation="http://www.loc.gov/mods/v3 http://www.loc.gov/standards/mods/v3/mods-3-3.xsd" version="3.3" ID="P0b002ee192e95a63">
<name type="corporate">
 <namePart>United States Government Publishing Office</namePart>
 <role>
  <roleTerm type="text" authority="marcrelator">publisher</roleTerm>
  <roleTerm type="code" authority="marcrelator">pbl</roleTerm>
</role>
 <role>
  <roleTerm type="text" authority="marcrelator">distributor</roleTerm>
  <roleTerm type="code" authority="marcrelator">dst</roleTerm>
</role>
</name>
<name type="corporate">
 <namePart>United States</namePart>
 <namePart>Congress</namePart>
 <namePart>Senate</namePart>
 <role>
  <roleTerm type="text" authority="marcrelator">author</roleTerm>
  <roleTerm type="code" authority="marcrelator">aut</roleTerm>
</role>
 <description>Government Organization</description>
</name>
<typeOfResource>text</typeOfResource>
<genre authority="marcgt">government publication</genre>
<language>
 <languageTerm authority="iso639-2b" type="code">eng</languageTerm>
</language>
<extension>
 <collectionCode>BILLS</collectionCode>
 <searchTitle>Recognizing the vital role the Civil Air Patrol has played, and continues to play, in supporting the homeland security and national defense of the United States.;S. Res. 623 (ATS)</searchTitle>
 <category>Bills and Statutes</category>
 <waisDatabaseName>114_cong_bills</waisDatabaseName>
 <branch>legislative</branch>
 <dateIngested>2016-11-30</dateIngested>
</extension>
<titleInfo>
 <title>Recognizing the vital role the Civil Air Patrol has played, and continues to play, in supporting the homeland security and national defense of the United States.</title>
</titleInfo>
<titleInfo type="alternative">
 <title>S. Res. 623 (ATS)</title>
</titleInfo>
<originInfo>
 <publisher>U.S. Government Publishing Office</publisher>
 <dateIssued encoding="w3cdtf">2016-11-29</dateIssued>
 <issuance>monographic</issuance>
</originInfo>
<physicalDescription>
 <note type="source content type">deposited</note>
 <digitalOrigin>born digital</digitalOrigin>
 <extent>4 p.</extent>
</physicalDescription>
<classification authority="sudocs">Y 1.6:</classification>
<classification authority="sudocs">Y 1.4/2:</classification>
<identifier type="local">P0b002ee192e95a63</identifier>
<identifier type="uri">https://www.gpo.gov/fdsys/pkg/BILLS-114sres623ats</identifier>
<identifier type="preferred citation">S. Res. 623</identifier>
<identifier type="stock number">021-610-00252-9</identifier>
<identifier type="Parent ILS system id">000501532</identifier>
<identifier type="Child ILS system id">000325577</identifier>
<identifier type="Parent ILS title">Congressional bills</identifier>
<identifier type="Child ILS title">Senate resolutions</identifier>
<identifier type="former package identifier">f:sr623_ats.txt</identifier>
<location xmlns:exslt="http://exslt.org/common">
 <url access="object in context" displayLabel="Content Detail">https://www.gpo.gov/fdsys/pkg/BILLS-114sres623ats/content-detail.html</url>
 <url access="raw object" displayLabel="HTML rendition">https://www.gpo.gov/fdsys/pkg/BILLS-114sres623ats/html/BILLS-114sres623ats.htm</url>
 <url access="raw object" displayLabel="PDF rendition">https://www.gpo.gov/fdsys/pkg/BILLS-114sres623ats/pdf/BILLS-114sres623ats.pdf</url>
 <url access="raw object" displayLabel="XML rendition">https://www.gpo.gov/fdsys/pkg/BILLS-114sres623ats/xml/BILLS-114sres623ats.xml</url>
</location>
<accessCondition type="GPO scope determination">fdlp</accessCondition>
<recordInfo>
 <recordContentSource authority="marcorg">DGPO</recordContentSource>
 <recordCreationDate encoding="w3cdtf">2016-11-30</recordCreationDate>
 <recordChangeDate encoding="w3cdtf">2016-12-01</recordChangeDate>
 <recordIdentifier source="DGPO">BILLS-114sres623ats</recordIdentifier>
 <recordOrigin>machine generated</recordOrigin>
 <languageOfCataloging>
  <languageTerm authority="iso639-2b" type="code">eng</languageTerm>
</languageOfCataloging>
</recordInfo>
<name type="personal">
 <namePart>Susan M. Collins</namePart>
 <affiliation>United States Senate</affiliation>
 <role>
  <roleTerm type="text" authority="marcrelator">sponsor</roleTerm>
  <roleTerm type="code" authority="marcrelator">spn</roleTerm>
</role>
 <description>United States Congress Member</description>
</name>
<name type="personal">
 <namePart>Barbara A. Mikulski</namePart>
 <affiliation>United States Senate</affiliation>
 <role>
  <roleTerm type="text">cosponsor</roleTerm>
</role>
 <description>United States Congress Member</description>
</name>
<name type="personal">
 <namePart>Richard Blumenthal</namePart>
 <affiliation>United States Senate</affiliation>
 <role>
  <roleTerm type="text">cosponsor</roleTerm>
</role>
 <description>United States Congress Member</description>
</name>
<name type="personal">
 <namePart>Lisa Murkowski</namePart>
 <affiliation>United States Senate</affiliation>
 <role>
  <roleTerm type="text">cosponsor</roleTerm>
</role>
 <description>United States Congress Member</description>
</name>
<name type="personal">
 <namePart>Jon Tester</namePart>
 <affiliation>United States Senate</affiliation>
 <role>
  <roleTerm type="text">cosponsor</roleTerm>
</role>
 <description>United States Congress Member</description>
</name>
<name type="personal">
 <namePart>Roger F. Wicker</namePart>
 <affiliation>United States Senate</affiliation>
 <role>
  <roleTerm type="text">cosponsor</roleTerm>
</role>
 <description>United States Congress Member</description>
</name>
<name type="personal">
 <namePart>Sheldon Whitehouse</namePart>
 <affiliation>United States Senate</affiliation>
 <role>
  <roleTerm type="text">cosponsor</roleTerm>
</role>
 <description>United States Congress Member</description>
</name>
<name type="personal">
 <namePart>Patrick J. Toomey</namePart>
 <affiliation>United States Senate</affiliation>
 <role>
  <roleTerm type="text">cosponsor</roleTerm>
</role>
 <description>United States Congress Member</description>
</name>
<name type="personal">
 <namePart>Jeanne Shaheen</namePart>
 <affiliation>United States Senate</affiliation>
 <role>
  <roleTerm type="text">cosponsor</roleTerm>
</role>
 <description>United States Congress Member</description>
</name>
<name type="personal">
 <namePart>Mark Kirk</namePart>
 <affiliation>United States Senate</affiliation>
 <role>
  <roleTerm type="text">cosponsor</roleTerm>
</role>
 <description>United States Congress Member</description>
</name>
<name type="personal">
 <namePart>Mazie K. Hirono</namePart>
 <affiliation>United States Senate</affiliation>
 <role>
  <roleTerm type="text">cosponsor</roleTerm>
</role>
 <description>United States Congress Member</description>
</name>
<name type="personal">
 <namePart>Pat Roberts</namePart>
 <affiliation>United States Senate</affiliation>
 <role>
  <roleTerm type="text">cosponsor</roleTerm>
</role>
 <description>United States Congress Member</description>
</name>
<name type="personal">
 <namePart>Ron Wyden</namePart>
 <affiliation>United States Senate</affiliation>
 <role>
  <roleTerm type="text">cosponsor</roleTerm>
</role>
 <description>United States Congress Member</description>
</name>
<name type="personal">
 <namePart>James M. Inhofe</namePart>
 <affiliation>United States Senate</affiliation>
 <role>
  <roleTerm type="text">cosponsor</roleTerm>
</role>
 <description>United States Congress Member</description>
</name>
<name type="personal">
 <namePart>Barbara Boxer</namePart>
 <affiliation>United States Senate</affiliation>
 <role>
  <roleTerm type="text">cosponsor</roleTerm>
</role>
 <description>United States Congress Member</description>
</name>
<name type="personal">
 <namePart>Cory Gardner</namePart>
 <affiliation>United States Senate</affiliation>
 <role>
  <roleTerm type="text">cosponsor</roleTerm>
</role>
 <description>United States Congress Member</description>
</name>
<name type="personal">
 <namePart>Christopher A. Coons</namePart>
 <affiliation>United States Senate</affiliation>
 <role>
  <roleTerm type="text">cosponsor</roleTerm>
</role>
 <description>United States Congress Member</description>
</name>
<name type="personal">
 <namePart>Orrin G. Hatch</namePart>
 <affiliation>United States Senate</affiliation>
 <role>
  <roleTerm type="text">cosponsor</roleTerm>
</role>
 <description>United States Congress Member</description>
</name>
<name type="personal">
 <namePart>Gary C. Peters</namePart>
 <affiliation>United States Senate</affiliation>
 <role>
  <roleTerm type="text">cosponsor</roleTerm>
</role>
 <description>United States Congress Member</description>
</name>
<name type="personal">
 <namePart>James Lankford</namePart>
 <affiliation>United States Senate</affiliation>
 <role>
  <roleTerm type="text">cosponsor</roleTerm>
</role>
 <description>United States Congress Member</description>
</name>
<name type="personal">
 <namePart>Bill Nelson</namePart>
 <affiliation>United States Senate</affiliation>
 <role>
  <roleTerm type="text">cosponsor</roleTerm>
</role>
 <description>United States Congress Member</description>
</name>
<name type="personal">
 <namePart>John Thune</namePart>
 <affiliation>United States Senate</affiliation>
 <role>
  <roleTerm type="text">cosponsor</roleTerm>
</role>
 <description>United States Congress Member</description>
</name>
<name type="personal">
 <namePart>Robert Menendez</namePart>
 <affiliation>United States Senate</affiliation>
 <role>
  <roleTerm type="text">cosponsor</roleTerm>
</role>
 <description>United States Congress Member</description>
</name>
<name type="personal">
 <namePart>Dan Sullivan</namePart>
 <affiliation>United States Senate</affiliation>
 <role>
  <roleTerm type="text">cosponsor</roleTerm>
</role>
 <description>United States Congress Member</description>
</name>
<name type="personal">
 <namePart>Thomas R. Carper</namePart>
 <affiliation>United States Senate</affiliation>
 <role>
  <roleTerm type="text">cosponsor</roleTerm>
</role>
 <description>United States Congress Member</description>
</name>
<name type="personal">
 <namePart>Kelly Ayotte</namePart>
 <affiliation>United States Senate</affiliation>
 <role>
  <roleTerm type="text">cosponsor</roleTerm>
</role>
 <description>United States Congress Member</description>
</name>
<name type="personal">
 <namePart>Tammy Baldwin</namePart>
 <affiliation>United States Senate</affiliation>
 <role>
  <roleTerm type="text">cosponsor</roleTerm>
</role>
 <description>United States Congress Member</description>
</name>
<name type="personal">
 <namePart>Mike Crapo</namePart>
 <affiliation>United States Senate</affiliation>
 <role>
  <roleTerm type="text">cosponsor</roleTerm>
</role>
 <description>United States Congress Member</description>
</name>
<name type="personal">
 <namePart>Martin Heinrich</namePart>
 <affiliation>United States Senate</affiliation>
 <role>
  <roleTerm type="text">cosponsor</roleTerm>
</role>
 <description>United States Congress Member</description>
</name>
<name type="personal">
 <namePart>Tom Cotton</namePart>
 <affiliation>United States Senate</affiliation>
 <role>
  <roleTerm type="text">cosponsor</roleTerm>
</role>
 <description>United States Congress Member</description>
</name>
<name type="personal">
 <namePart>Tom Udall</namePart>
 <affiliation>United States Senate</affiliation>
 <role>
  <roleTerm type="text">cosponsor</roleTerm>
</role>
 <description>United States Congress Member</description>
</name>
<name type="personal">
 <namePart>Roy Blunt</namePart>
 <affiliation>United States Senate</affiliation>
 <role>
  <roleTerm type="text">cosponsor</roleTerm>
</role>
 <description>United States Congress Member</description>
</name>
<name type="personal">
 <namePart>Robert P. Casey Jr.</namePart>
 <affiliation>United States Senate</affiliation>
 <role>
  <roleTerm type="text">cosponsor</roleTerm>
</role>
 <description>United States Congress Member</description>
</name>
<name type="personal">
 <namePart>Shelley Moore Capito</namePart>
 <affiliation>United States Senate</affiliation>
 <role>
  <roleTerm type="text">cosponsor</roleTerm>
</role>
 <description>United States Congress Member</description>
</name>
<name type="personal">
 <namePart>Angus S. King Jr.</namePart>
 <affiliation>United States Senate</affiliation>
 <role>
  <roleTerm type="text">cosponsor</roleTerm>
</role>
 <description>United States Congress Member</description>
</name>
<name type="personal">
 <namePart>Mike Rounds</namePart>
 <affiliation>United States Senate</affiliation>
 <role>
  <roleTerm type="text">cosponsor</roleTerm>
</role>
 <description>United States Congress Member</description>
</name>
<name type="personal">
 <namePart>Edward J. Markey</namePart>
 <affiliation>United States Senate</affiliation>
 <role>
  <roleTerm type="text">cosponsor</roleTerm>
</role>
 <description>United States Congress Member</description>
</name>
<name type="personal">
 <namePart>Michael F. Bennet</namePart>
 <affiliation>United States Senate</affiliation>
 <role>
  <roleTerm type="text">cosponsor</roleTerm>
</role>
 <description>United States Congress Member</description>
</name>
<name type="personal">
 <namePart>Al Franken</namePart>
 <affiliation>United States Senate</affiliation>
 <role>
  <roleTerm type="text">cosponsor</roleTerm>
</role>
 <description>United States Congress Member</description>
</name>
<name type="personal">
 <namePart>Joe Manchin III</namePart>
 <affiliation>United States Senate</affiliation>
 <role>
  <roleTerm type="text">cosponsor</roleTerm>
</role>
 <description>United States Congress Member</description>
</name>
<name type="personal">
 <namePart>David Perdue</namePart>
 <affiliation>United States Senate</affiliation>
 <role>
  <roleTerm type="text">cosponsor</roleTerm>
</role>
 <description>United States Congress Member</description>
</name>
<extension>
 <docClass>sres</docClass>
 <accessId>BILLS-114sres623ats</accessId>
 <congress>114</congress>
 <session>2</session>
 <originChamber>SENATE</originChamber>
 <currentChamber>SENATE</currentChamber>
 <billNumber>623</billNumber>
 <billVersion reprint="false">ats</billVersion>
 <fileSuffix>ats</fileSuffix>
 <officialTitle>Recognizing the vital role the Civil Air Patrol has played, and continues to play, in supporting the homeland security and national defense of the United States.</officialTitle>
 <action date="2016-11-29">Ms. Collins (for herself, Ms. Mikulski, Mr. Blumenthal, Ms. Murkowski, Mr. Tester, Mr. Wicker, Mr. Whitehouse, Mr. Toomey, Mrs. Shaheen, Mr. Kirk, Ms. Hirono, Mr. Roberts, Mr. Wyden, Mr. Inhofe, Mrs. Boxer, Mr. Gardner, Mr. Coons, Mr. Hatch, Mr. Peters, Mr. Lankford, Mr. Nelson, Mr. Thune, Mr. Menendez, Mr. Sullivan, Mr. Carper, Ms. Ayotte, Ms. Baldwin, Mr. Crapo, Mr. Heinrich, Mr. Cotton, Mr. Udall, Mr. Blunt, Mr. Casey, Mrs. Capito, Mr. King, Mr. Rounds, Mr. Markey, Mr. Bennet, Mr. Franken, Mr. Manchin, and Mr. Perdue) submitted the following resolution; which was considered and agreed to</action>
 <congMember authorityId="1541" bioGuideId="C001035" chamber="S" congress="114" gpoId="8291" party="R" role="SPONSOR" state="ME">
                      <name type="parsed">Ms. Collins</name>
                      <name type="authority-fnf">Susan M. Collins</name>
                      <name type="authority-lnf">Collins, Susan M.</name>
                      <name type="authority-other">Susan Margaret Collins</name>
                </congMember>
 <congMember authorityId="802" bioGuideId="M000702" chamber="S" congress="114" gpoId="8240" party="D" role="COSPONSOR" state="MD">
                      <name type="parsed">Ms. Mikulski</name>
                      <name type="authority-fnf">Barbara A. Mikulski</name>
                      <name type="authority-lnf">Mikulski, Barbara A.</name>
                      <name type="authority-other">Barbara Ann Mikulski</name>
                </congMember>
 <congMember authorityId="2076" bioGuideId="B001277" chamber="S" congress="114" gpoId="8332" party="D" role="COSPONSOR" state="CT">
                      <name type="parsed">Mr. Blumenthal</name>
                      <name type="authority-fnf">Richard Blumenthal</name>
                      <name type="authority-lnf">Blumenthal, Richard</name>
                </congMember>
 <congMember authorityId="1694" bioGuideId="M001153" chamber="S" congress="114" gpoId="8234" party="R" role="COSPONSOR" state="AK">
                      <name type="parsed">Ms. Murkowski</name>
                      <name type="authority-fnf">Lisa Murkowski</name>
                      <name type="authority-lnf">Murkowski, Lisa</name>
                </congMember>
 <congMember authorityId="1829" bioGuideId="T000464" chamber="S" congress="114" gpoId="8258" party="D" role="COSPONSOR" state="MT">
                      <name type="parsed">Mr. Tester</name>
                      <name type="authority-fnf">Jon Tester</name>
                      <name type="authority-lnf">Tester, Jon</name>
                </congMember>
 <congMember authorityId="1226" bioGuideId="W000437" chamber="S" congress="114" gpoId="8263" party="R" role="COSPONSOR" state="MS">
                      <name type="parsed">Mr. Wicker</name>
                      <name type="authority-fnf">Roger F. Wicker</name>
                      <name type="authority-lnf">Wicker, Roger F.</name>
                      <name type="authority-other">Roger Wicker</name>
                </congMember>
 <congMember authorityId="1823" bioGuideId="W000802" chamber="S" congress="114" gpoId="8264" party="D" role="COSPONSOR" state="RI">
                      <name type="parsed">Mr. Whitehouse</name>
                      <name type="authority-fnf">Sheldon Whitehouse</name>
                      <name type="authority-lnf">Whitehouse, Sheldon</name>
                </congMember>
 <congMember authorityId="1594" bioGuideId="T000461" chamber="S" congress="114" party="R" role="COSPONSOR" state="PA">
                      <name type="parsed">Mr. Toomey</name>
                      <name type="authority-fnf">Patrick J. Toomey</name>
                      <name type="authority-lnf">Toomey, Patrick J.</name>
                      <name type="authority-other">Patrick Toomey</name>
                </congMember>
 <congMember authorityId="1901" bioGuideId="S001181" chamber="S" congress="114" gpoId="8276" party="D" role="COSPONSOR" state="NH">
                      <name type="parsed">Mrs. Shaheen</name>
                      <name type="authority-fnf">Jeanne Shaheen</name>
                      <name type="authority-lnf">Shaheen, Jeanne</name>
                </congMember>
 <congMember authorityId="1647" bioGuideId="K000360" chamber="S" congress="114" gpoId="8285" party="R" role="COSPONSOR" state="IL">
                      <name type="parsed">Mr. Kirk</name>
                      <name type="authority-fnf">Mark Kirk</name>
                      <name type="authority-lnf">Kirk, Mark Steven</name>
                      <name type="authority-other">Mark Steven Kirk</name>
                </congMember>
 <congMember authorityId="1844" bioGuideId="H001042" chamber="S" congress="114" gpoId="7913" party="D" role="COSPONSOR" state="HI">
                      <name type="parsed">Ms. Hirono</name>
                      <name type="authority-fnf">Mazie K. Hirono</name>
                      <name type="authority-lnf">Hirono, Mazie K.</name>
                      <name type="authority-other">Ms. Mazie Hirono</name>
                </congMember>
 <congMember authorityId="968" bioGuideId="R000307" chamber="S" congress="114" gpoId="8275" party="R" role="COSPONSOR" state="KS">
                      <name type="parsed">Mr. Roberts</name>
                      <name type="authority-fnf">Pat Roberts</name>
                      <name type="authority-lnf">Roberts, Pat</name>
                </congMember>
 <congMember authorityId="1247" bioGuideId="W000779" chamber="S" congress="114" gpoId="8265" party="D" role="COSPONSOR" state="OR">
                      <name type="parsed">Mr. Wyden</name>
                      <name type="authority-fnf">Ron Wyden</name>
                      <name type="authority-lnf">Wyden, Ron</name>
                </congMember>
 <congMember authorityId="583" bioGuideId="I000024" chamber="S" congress="114" gpoId="8322" party="R" role="COSPONSOR" state="OK">
                      <name type="parsed">Mr. Inhofe</name>
                      <name type="authority-fnf">James M. Inhofe</name>
                      <name type="authority-lnf">Inhofe, James M.</name>
                      <name type="authority-other">Jim Inhofe</name>
                </congMember>
 <congMember authorityId="116" bioGuideId="B000711" chamber="S" congress="114" gpoId="8306" party="D" role="COSPONSOR" state="CA">
                      <name type="parsed">Mrs. Boxer</name>
                      <name type="authority-fnf">Barbara Boxer</name>
                      <name type="authority-lnf">Boxer, Barbara</name>
                </congMember>
 <congMember authorityId="1998" bioGuideId="G000562" chamber="S" congress="114" gpoId="7862" party="R" role="COSPONSOR" state="CO">
                      <name type="parsed">Mr. Gardner</name>
                      <name type="authority-fnf">Cory Gardner</name>
                      <name type="authority-lnf">Gardner, Cory</name>
                </congMember>
 <congMember authorityId="1984" bioGuideId="C001088" chamber="S" congress="114" gpoId="8297" party="D" role="COSPONSOR" state="DE">
                      <name type="parsed">Mr. Coons</name>
                      <name type="authority-fnf">Christopher A. Coons</name>
                      <name type="authority-lnf">Coons, Christopher A.</name>
                      <name type="authority-other">Mr. Christopher Coons</name>
                </congMember>
 <congMember authorityId="1351" bioGuideId="H000338" chamber="S" congress="114" gpoId="8314" party="R" role="COSPONSOR" state="UT">
                      <name type="parsed">Mr. Hatch</name>
                      <name type="authority-fnf">Orrin G. Hatch</name>
                      <name type="authority-lnf">Hatch, Orrin G.</name>
                      <name type="authority-other">Orrin Grant Hatch</name>
                </congMember>
 <congMember authorityId="1929" bioGuideId="P000595" chamber="S" congress="114" gpoId="7994" party="D" role="COSPONSOR" state="MI">
                      <name type="parsed">Mr. Peters</name>
                      <name type="authority-fnf">Gary C. Peters</name>
                      <name type="authority-lnf">Peters, Gary C.</name>
                      <name type="authority-other">Mr. Gary Peters</name>
                </congMember>
 <congMember authorityId="2050" bioGuideId="L000575" chamber="S" congress="114" gpoId="8113" party="R" role="COSPONSOR" state="OK">
                      <name type="parsed">Mr. Lankford</name>
                      <name type="authority-fnf">James Lankford</name>
                      <name type="authority-lnf">Lankford, James</name>
                </congMember>
 <congMember authorityId="859" bioGuideId="N000032" chamber="S" congress="114" gpoId="8236" party="D" role="COSPONSOR" state="FL">
                      <name type="parsed">Mr. Nelson</name>
                      <name type="authority-fnf">Bill Nelson</name>
                      <name type="authority-lnf">Nelson, Bill</name>
                      <name type="authority-other">Clarence William Nelson</name>
                </congMember>
 <congMember authorityId="1534" bioGuideId="T000250" chamber="S" congress="114" gpoId="8257" party="R" role="COSPONSOR" state="SD">
                      <name type="parsed">Mr. Thune</name>
                      <name type="authority-fnf">John Thune</name>
                      <name type="authority-lnf">Thune, John</name>
                      <name type="authority-other">John R. Thune</name>
                </congMember>
 <congMember authorityId="791" bioGuideId="M000639" chamber="S" congress="114" gpoId="8239" party="D" role="COSPONSOR" state="NJ">
                      <name type="parsed">Mr. Menendez</name>
                      <name type="authority-fnf">Robert Menendez</name>
                      <name type="authority-lnf">Menendez, Robert</name>
                </congMember>
 <congMember authorityId="2290" bioGuideId="S001198" chamber="S" congress="114" party="R" role="COSPONSOR" state="AK">
                      <name type="parsed">Mr. Sullivan</name>
                      <name type="authority-fnf">Dan Sullivan</name>
                      <name type="authority-lnf">Sullivan, Dan</name>
                </congMember>
 <congMember authorityId="179" bioGuideId="C000174" chamber="S" congress="114" gpoId="8283" party="D" role="COSPONSOR" state="DE">
                      <name type="parsed">Mr. Carper</name>
                      <name type="authority-fnf">Thomas R. Carper</name>
                      <name type="authority-lnf">Carper, Thomas R.</name>
                      <name type="authority-other">Thomas Carper</name>
                </congMember>
 <congMember authorityId="2075" bioGuideId="A000368" chamber="S" congress="114" gpoId="8315" party="R" role="COSPONSOR" state="NH">
                      <name type="parsed">Ms. Ayotte</name>
                      <name type="authority-fnf">Kelly Ayotte</name>
                      <name type="authority-lnf">Ayotte, Kelly</name>
                </congMember>
 <congMember authorityId="1558" bioGuideId="B001230" chamber="S" congress="114" gpoId="8215" party="D" role="COSPONSOR" state="WI">
                      <name type="parsed">Ms. Baldwin</name>
                      <name type="authority-fnf">Tammy Baldwin</name>
                      <name type="authority-lnf">Baldwin, Tammy</name>
                </congMember>
 <congMember authorityId="250" bioGuideId="C000880" chamber="S" congress="114" gpoId="8289" party="R" role="COSPONSOR" state="ID">
                      <name type="parsed">Mr. Crapo</name>
                      <name type="authority-fnf">Mike Crapo</name>
                      <name type="authority-lnf">Crapo, Mike</name>
                      <name type="authority-other">Michael Crapo</name>
                </congMember>
 <congMember authorityId="1937" bioGuideId="H001046" chamber="S" congress="114" gpoId="8056" party="D" role="COSPONSOR" state="NM">
                      <name type="parsed">Mr. Heinrich</name>
                      <name type="authority-fnf">Martin Heinrich</name>
                      <name type="authority-lnf">Heinrich, Martin</name>
                </congMember>
 <congMember authorityId="2098" bioGuideId="C001095" chamber="S" congress="114" party="R" role="COSPONSOR" state="AR">
                      <name type="parsed">Mr. Cotton</name>
                      <name type="authority-fnf">Tom Cotton</name>
                      <name type="authority-lnf">Cotton, Tom</name>
                </congMember>
 <congMember authorityId="1567" bioGuideId="U000039" chamber="S" congress="114" gpoId="8260" party="D" role="COSPONSOR" state="NM">
                      <name type="parsed">Mr. Udall</name>
                      <name type="authority-fnf">Tom Udall</name>
                      <name type="authority-lnf">Udall, Tom</name>
                </congMember>
 <congMember authorityId="1464" bioGuideId="B000575" chamber="S" congress="114" gpoId="8313" party="R" role="COSPONSOR" state="MO">
                      <name type="parsed">Mr. Blunt</name>
                      <name type="authority-fnf">Roy Blunt</name>
                      <name type="authority-lnf">Blunt, Roy</name>
                </congMember>
 <congMember authorityId="1828" bioGuideId="C001070" chamber="S" congress="114" gpoId="8282" party="D" role="COSPONSOR" state="PA">
                      <name type="parsed">Mr. Casey</name>
                      <name type="authority-fnf">Robert P. Casey Jr.</name>
                      <name type="authority-lnf">Casey, Robert P., Jr.</name>
                      <name type="authority-other">Mr. Bob Casey Jr.</name>
                </congMember>
 <congMember authorityId="1676" bioGuideId="C001047" chamber="S" congress="114" gpoId="8223" party="R" role="COSPONSOR" state="WV">
                      <name type="parsed">Mrs. Capito</name>
                      <name type="authority-fnf">Shelley Moore Capito</name>
                      <name type="authority-lnf">Capito, Shelley Moore</name>
                      <name type="authority-other">Shelley Capito</name>
                </congMember>
 <congMember authorityId="2185" bioGuideId="K000383" chamber="S" congress="114" party="I" role="COSPONSOR" state="ME">
                      <name type="parsed">Mr. King</name>
                      <name type="authority-fnf">Angus S. King Jr.</name>
                      <name type="authority-lnf">King, Angus S., Jr.</name>
                      <name type="authority-other">Mr. Angus King Jr.</name>
                </congMember>
 <congMember authorityId="2288" bioGuideId="R000605" chamber="S" congress="114" party="R" role="COSPONSOR" state="SD">
                      <name type="parsed">Mr. Rounds</name>
                      <name type="authority-fnf">Mike Rounds</name>
                      <name type="authority-lnf">Rounds, Mike</name>
                </congMember>
 <congMember authorityId="735" bioGuideId="M000133" chamber="S" congress="114" gpoId="7972" party="D" role="COSPONSOR" state="MA">
                      <name type="parsed">Mr. Markey</name>
                      <name type="authority-fnf">Edward J. Markey</name>
                      <name type="authority-lnf">Markey, Edward J.</name>
                      <name type="authority-other">Edward Markey</name>
                </congMember>
 <congMember authorityId="1965" bioGuideId="B001267" chamber="S" congress="114" gpoId="8302" party="D" role="COSPONSOR" state="CO">
                      <name type="parsed">Mr. Bennet</name>
                      <name type="authority-fnf">Michael F. Bennet</name>
                      <name type="authority-lnf">Bennet, Michael F.</name>
                      <name type="authority-other">Mr. Michael Bennet</name>
                </congMember>
 <congMember authorityId="1969" bioGuideId="F000457" chamber="S" congress="114" gpoId="8339" party="D" role="COSPONSOR" state="MN">
                      <name type="parsed">Mr. Franken</name>
                      <name type="authority-fnf">Al Franken</name>
                      <name type="authority-lnf">Franken, Al</name>
                </congMember>
 <congMember authorityId="1983" bioGuideId="M001183" chamber="S" congress="114" gpoId="8256" party="D" role="COSPONSOR" state="WV">
                      <name type="parsed">Mr. Manchin</name>
                      <name type="authority-fnf">Joe Manchin III</name>
                      <name type="authority-lnf">Manchin, Joe, III</name>
                      <name type="authority-other">Mr. Joe Manchin III</name>
                </congMember>
 <congMember authorityId="2286" bioGuideId="P000612" chamber="S" congress="114" party="R" role="COSPONSOR" state="GA">
                      <name type="parsed">Mr. Perdue</name>
                      <name type="authority-fnf">David Perdue</name>
                      <name type="authority-lnf">Perdue, David</name>
                      <name type="authority-other">Mr. David Alfred Perdue</name>
                </congMember>
 <isPrivate>false</isPrivate>
 <isAppropriation>false</isAppropriation>
</extension>
</mods>